defected/__init__.py
defected/main.py
defected/api/__init__.py
defected/cmds/__init__.py
defected/cmds/analyze.py
defected/cmds/inspect.py
defected/cmds/investigate.py
defected-0.5.1.dist-info/METADATA
defected-0.5.1.dist-info/WHEEL
defected-0.5.1.dist-info/entry_points.txt
defected-0.5.1.dist-info/licenses/LICENSE
defected-0.5.1.dist-info/RECORD
