Metadata-Version: 2.3
Name: defected
Version: 0.5.1
Summary: Detect suspicious behaviors in git repos and open-source projects.
Project-URL: Homepage, https://github.com/4383/defected
Project-URL: History, https://github.com/4383/defected/blob/main/CHANGELOG.md
Project-URL: Sponsor, https://github.com/sponsors/4383
Project-URL: Tracker, https://github.com/4383/defected/issues
Project-URL: Source, https://github.com/4383/defected
Author-email: Hervé Beraud <herveberaud.pro@gmail.com>
License: MIT
Classifier: Development Status :: 3 - Alpha
Classifier: Environment :: Console
Classifier: Intended Audience :: Developers
Classifier: License :: OSI Approved :: MIT License
Classifier: Operating System :: OS Independent
Classifier: Programming Language :: Python
Classifier: Programming Language :: Python :: 3
Classifier: Programming Language :: Python :: 3.11
Classifier: Programming Language :: Python :: 3.12
Classifier: Topic :: Security
Classifier: Topic :: Sociology
Classifier: Topic :: Software Development
Requires-Python: >=3.8
Requires-Dist: pandas
Requires-Dist: timezonefinder
Provides-Extra: dev
Requires-Dist: black; extra == 'dev'
Requires-Dist: build; extra == 'dev'
Requires-Dist: commitizen; extra == 'dev'
Requires-Dist: isort; extra == 'dev'
Requires-Dist: pip-tools; extra == 'dev'
Requires-Dist: pre-commit; extra == 'dev'
Requires-Dist: twine; extra == 'dev'
